yacht/__init__.py
yacht/__main__.py
yacht/anchor.py
yacht/convert.py
yacht/help.py
yacht/sail.py
yacht-0.4.3.dist-info/METADATA
yacht-0.4.3.dist-info/WHEEL
yacht-0.4.3.dist-info/licenses/LICENSE
yacht-0.4.3.dist-info/RECORD
