Metadata-Version: 2.1
Name: yacht
Version: 0.4.3
Summary: YAML conveter to HTML
Project-URL: Homepage, https://github.com/Pobulus/yacht
Project-URL: Issues, https://github.com/Pobulus/yacht/issues
Author-email: Pobulus <pawek.chmielewski@gmail.com>
License-File: LICENSE
Classifier: License :: OSI Approved :: GNU General Public License v3 (GPLv3)
Classifier: Operating System :: OS Independent
Classifier: Programming Language :: Python :: 3
Requires-Python: >=3.8
Requires-Dist: pyyaml>=6.0.1
